atlasdcat/__init__.py
atlasdcat/attribute.py
atlasdcat/glossaryclient.py
atlasdcat/mapper.py
atlasdcat/termtype.py
atlasdcat-1.1.2.dist-info/LICENSE
atlasdcat-1.1.2.dist-info/WHEEL
atlasdcat-1.1.2.dist-info/METADATA
atlasdcat-1.1.2.dist-info/RECORD
