Metadata-Version: 2.1
Name: atlasdcat
Version: 1.1.2
Summary: A library for managing DCAT metadata using Apache Atlas
Home-page: https://github.com/Informasjonsforvaltning/atlasdcat
License: Apache-2.0
Author: Jeff Reiffers
Author-email: jeff@ouvir.no
Requires-Python: >=3.8,<3.11
Classifier: License :: OSI Approved :: Apache Software License
Classifier: Operating System :: OS Independent
Classifier: Programming Language :: Python :: 3
Classifier: Programming Language :: Python :: 3.10
Classifier: Programming Language :: Python :: 3.8
Classifier: Programming Language :: Python :: 3.9
Requires-Dist: black (>=22.10.0,<23.0.0)
Requires-Dist: coverage (>=6.5.0,<7.0.0)
Requires-Dist: datacatalogtordf (>=3.0.0,<4.0.0)
Requires-Dist: pyapacheatlas (>=0.14.0,<0.15.0)
Project-URL: Documentation, https://atlasdcat.readthedocs.io
Project-URL: Repository, https://github.com/Informasjonsforvaltning/atlasdcat
